pyxbee/__init__.py
pyxbee/base.py
pyxbee/const.py
pyxbee/exception.py
pyxbee/packet.py
pyxbee-0.8.0.dist-info/LICENSE
pyxbee-0.8.0.dist-info/WHEEL
pyxbee-0.8.0.dist-info/METADATA
pyxbee-0.8.0.dist-info/RECORD
